tableDataParser/__init__.py
tableDataParser/__main__.py
tableParser/__init__.py
tableParser/__main__.py
tableParser-1.0.1.dist-info/METADATA
tableParser-1.0.1.dist-info/WHEEL
tableParser-1.0.1.dist-info/entry_points.txt
tableParser-1.0.1.dist-info/top_level.txt
tableParser-1.0.1.dist-info/RECORD
